{
  "get": "fixtures",
  "parameters": {
    "league": "203",
    "season": "2024",
    "from": "2025-05-08",
    "to": "2025-05-09"
  },
  "errors": [],
  "results": 2,
  "paging": {
    "current": 1,
    "total": 1
  },
  "response": [
    {
      "fixture": {
        "id": 1238160,
        "referee": null,
        "timezone": "UTC",
        "date": "2025-05-09T17:00:00+00:00",
        "timestamp": 1746810000,
        "periods": {
          "first": null,
          "second": null
        },
        "venue": {
          "id": 1584,
          "name": "Ba\u015fak\u015fehir Fatih Terim Stadyumu",
          "city": "\u0130stanbul"
        },
        "status": {
          "long": "Not Started",
          "short": "NS",
          "elapsed": null,
          "extra": null
        }
      },
      "league": {
        "id": 203,
        "name": "S\u00fcper Lig",
        "country": "Turkey",
        "logo": "https://media.api-sports.io/football/leagues/203.png",
        "flag": "https://media.api-sports.io/flags/tr.svg",
        "season": 2024,
        "round": "Regular Season - 35",
        "standings": true
      },
      "teams": {
        "home": {
          "id": 564,
          "name": "Istanbul Basaksehir",
          "logo": "https://media.api-sports.io/football/teams/564.png",
          "winner": null
        },
        "away": {
          "id": 611,
          "name": "Fenerbahce",
          "logo": "https://media.api-sports.io/football/teams/611.png",
          "winner": null
        }
      },
      "goals": {
        "home": null,
        "away": null
      },
      "score": {
        "halftime": {
          "home": null,
          "away": null
        },
        "fulltime": {
          "home": null,
          "away": null
        },
        "extratime": {
          "home": null,
          "away": null
        },
        "penalty": {
          "home": null,
          "away": null
        }
      }
    },
    {
      "fixture": {
        "id": 1238163,
        "referee": null,
        "timezone": "UTC",
        "date": "2025-05-09T17:00:00+00:00",
        "timestamp": 1746810000,
        "periods": {
          "first": null,
          "second": null
        },
        "venue": {
          "id": 2375,
          "name": "Gaziantep Stadyumu",
          "city": "Gaziantep"
        },
        "status": {
          "long": "Not Started",
          "short": "NS",
          "elapsed": null,
          "extra": null
        }
      },
      "league": {
        "id": 203,
        "name": "S\u00fcper Lig",
        "country": "Turkey",
        "logo": "https://media.api-sports.io/football/leagues/203.png",
        "flag": "https://media.api-sports.io/flags/tr.svg",
        "season": 2024,
        "round": "Regular Season - 35",
        "standings": true
      },
      "teams": {
        "home": {
          "id": 3573,
          "name": "Gazi\u015fehir Gaziantep",
          "logo": "https://media.api-sports.io/football/teams/3573.png",
          "winner": null
        },
        "away": {
          "id": 996,
          "name": "Alanyaspor",
          "logo": "https://media.api-sports.io/football/teams/996.png",
          "winner": null
        }
      },
      "goals": {
        "home": null,
        "away": null
      },
      "score": {
        "halftime": {
          "home": null,
          "away": null
        },
        "fulltime": {
          "home": null,
          "away": null
        },
        "extratime": {
          "home": null,
          "away": null
        },
        "penalty": {
          "home": null,
          "away": null
        }
      }
    }
  ]
}